{
 "1": {
  "user": "Me",
  "text": "Lorem, ipsum dolor sit amet consectetur adipisicing elit. Quidem, ratione",
  "chatId": "1"
 },
 "2": {
  "user": null,
  "text": "Lorem ipsum dolor sit amet",
  "chatId": "1"
 },
 "3": {
  "user": "Me",
  "text": "Lorem ipsum, dolor sit amet consectetur adipisicing elit. Architecto, voluptatum quasi?",
  "chatId": "2"
 },
 "4": {
  "user": null,
  "text": "Lorem ipsum dolor sit amet consectetur, adipisicing elit",
  "chatId": "2"
 },
 "5": {
  "user": "Me",
  "text": "Lorem",
  "chatId": "2"
 },
 "6": {
  "user": null,
  "text": "Lorem ipsum dolor sit amet",
  "chatId": "2"
 },
 "7": {
  "user": "Me",
  "text": "adfbadb asdfb asdfb ",
  "chatId": "1"
 },
 "8": {
  "user": "Me",
  "text": "adfgb sdfgb sdgfb sg sgb335463456",
  "chatId": "1"
 },
 "9": {
  "user": "Me",
  "text": "fhj,f",
  "chatId": "1"
 },
 "10": {
  "user": "Me",
  "text": "adfbadfb adfb",
  "chatId": "1"
 },
 "11": {
  "user": "Me",
  "text": "adfbadfgb dfbadfb adfb",
  "chatId": "1"
 },
 "12": {
  "user": "Me",
  "text": "впрьвпрь",
  "chatId": "1"
 }
}